smriti/__init__.py
smriti/cli.py
smriti/config.py
smriti/embeddings.py
smriti/enhanced_memory_manager.py
smriti/enterprise_security.py
smriti/exceptions.py
smriti/framework_adapters.py
smriti/graph_memory.py
smriti/hybrid_retrieval.py
smriti/llm.py
smriti/memory_manager.py
smriti/performance_optimizer.py
smriti/ultimate_memory_manager.py
smriti/vector_db.py
smriti/vector_stores.py
smriti_memory-0.2.0.dist-info/licenses/LICENSE
smriti_memory-0.2.0.dist-info/METADATA
smriti_memory-0.2.0.dist-info/WHEEL
smriti_memory-0.2.0.dist-info/entry_points.txt
smriti_memory-0.2.0.dist-info/top_level.txt
smriti_memory-0.2.0.dist-info/RECORD
