Metadata-Version: 2.4
Name: smriti-memory
Version: 0.2.0
Summary: An intelligent memory layer for AI applications with RAG capabilities
Author-email: Aman Kumar <ad721603@gmail.com>
Maintainer-email: Aman Kumar <ad721603@gmail.com>
License-Expression: MIT
Project-URL: Homepage, https://github.com/amanyadav721/smriti
Project-URL: Documentation, https://github.com/amanyadav721/smriti#readme
Project-URL: Repository, https://github.com/amanyadav721/smriti
Project-URL: Bug Tracker, https://github.com/amanyadav721/smriti/issues
Keywords: ai,memory,rag,vector-database,pinecone,llm,groq,gemini
Classifier: Development Status :: 3 - Alpha
Classifier: Intended Audience :: Developers
Classifier: Operating System :: OS Independent
Classifier: Programming Language :: Python :: 3
Classifier: Programming Language :: Python :: 3.8
Classifier: Programming Language :: Python :: 3.9
Classifier: Programming Language :: Python :: 3.10
Classifier: Programming Language :: Python :: 3.11
Classifier: Topic :: Scientific/Engineering :: Artificial Intelligence
Classifier: Topic :: Software Development :: Libraries :: Python Modules
Requires-Python: >=3.8
License-File: LICENSE
Requires-Dist: pinecone>=2.0.0
Requires-Dist: langchain>=0.3.0
Requires-Dist: langchain-groq>=0.3.0
Requires-Dist: langchain-google-genai>=2.0.0
Requires-Dist: python-dotenv>=1.0.0
Requires-Dist: pydantic>=2.0.0
Requires-Dist: fastapi>=0.100.0
Requires-Dist: uvicorn>=0.20.0
Provides-Extra: dev
Requires-Dist: pytest>=7.0.0; extra == "dev"
Requires-Dist: pytest-cov>=4.0.0; extra == "dev"
Requires-Dist: black>=23.0.0; extra == "dev"
Requires-Dist: flake8>=6.0.0; extra == "dev"
Requires-Dist: mypy>=1.0.0; extra == "dev"
Requires-Dist: pre-commit>=3.0.0; extra == "dev"
Provides-Extra: docs
Requires-Dist: sphinx>=6.0.0; extra == "docs"
Requires-Dist: sphinx-rtd-theme>=1.0.0; extra == "docs"
Dynamic: license-file
